plenopticam/__init__.py
plenopticam/main.py
plenopticam/bin/__init__.py
plenopticam/bin/cli_script.py
plenopticam/cfg/__init__.py
plenopticam/cfg/cfg.json
plenopticam/cfg/cfg.py
plenopticam/cfg/constants.py
plenopticam/gui/__init__.py
plenopticam/gui/constants.py
plenopticam/gui/top_level.py
plenopticam/gui/widget_about.py
plenopticam/gui/widget_cmnd.py
plenopticam/gui/widget_cnfg.py
plenopticam/gui/widget_ctrl.py
plenopticam/gui/widget_file.py
plenopticam/gui/widget_menu.py
plenopticam/gui/widget_path.py
plenopticam/gui/widget_pbar.py
plenopticam/gui/widget_view.py
plenopticam/gui/icns/1055104.gif
plenopticam/gui/icns/1055104.icns
plenopticam/gui/icns/1055104.ico
plenopticam/lfp_aligner/__init__.py
plenopticam/lfp_aligner/cfa_outliers.py
plenopticam/lfp_aligner/cfa_processor.py
plenopticam/lfp_aligner/lfp_devignetter.py
plenopticam/lfp_aligner/lfp_global_resampler.py
plenopticam/lfp_aligner/lfp_local_resampler.py
plenopticam/lfp_aligner/lfp_microlenses.py
plenopticam/lfp_aligner/lfp_resampler.py
plenopticam/lfp_aligner/lfp_rotator.py
plenopticam/lfp_aligner/top_level.py
plenopticam/lfp_calibrator/__init__.py
plenopticam/lfp_calibrator/cali_finder.py
plenopticam/lfp_calibrator/centroid_drawer.py
plenopticam/lfp_calibrator/centroid_extractor.py
plenopticam/lfp_calibrator/centroid_fit_sort.py
plenopticam/lfp_calibrator/centroid_refiner.py
plenopticam/lfp_calibrator/centroid_sorter.py
plenopticam/lfp_calibrator/find_centroid.py
plenopticam/lfp_calibrator/grid_fitter.py
plenopticam/lfp_calibrator/line_fitter.py
plenopticam/lfp_calibrator/non_max_supp.py
plenopticam/lfp_calibrator/pitch_estimator.py
plenopticam/lfp_calibrator/top_level.py
plenopticam/lfp_extractor/__init__.py
plenopticam/lfp_extractor/hex_corrector.py
plenopticam/lfp_extractor/lfp_color_eq.py
plenopticam/lfp_extractor/lfp_contrast.py
plenopticam/lfp_extractor/lfp_cropper.py
plenopticam/lfp_extractor/lfp_depth.py
plenopticam/lfp_extractor/lfp_exporter.py
plenopticam/lfp_extractor/lfp_outliers.py
plenopticam-0.9.3.dist-info/LICENSE.rst
plenopticam-0.9.3.dist-info/METADATA
plenopticam-0.9.3.dist-info/WHEEL
plenopticam-0.9.3.dist-info/entry_points.txt
plenopticam-0.9.3.dist-info/top_level.txt
plenopticam-0.9.3.dist-info/RECORD
